{
  "teams": [
    {
      "team": "COL",
      "name": "Colorado Avalanche",
      "round1_win_pct": 1.0,
      "round2_win_pct": 0.8249,
      "round3_win_pct": 0.6743,
      "cup_win_pct": 0.4188,
      "current_series": "4-0",
      "opponent": "LAK"
    },
    {
      "team": "CAR",
      "name": "Carolina Hurricanes",
      "round1_win_pct": 1.0,
      "round2_win_pct": 0.7002,
      "round3_win_pct": 0.471,
      "cup_win_pct": 0.2675,
      "current_series": "4-0",
      "opponent": "OTT"
    },
    {
      "team": "BUF",
      "name": "Buffalo Sabres",
      "round1_win_pct": 1.0,
      "round2_win_pct": 0.5977,
      "round3_win_pct": 0.2298,
      "cup_win_pct": 0.0824,
      "current_series": "4-2",
      "opponent": "BOS"
    },
    {
      "team": "PHI",
      "name": "Philadelphia Flyers",
      "round1_win_pct": 1.0,
      "round2_win_pct": 0.2999,
      "round3_win_pct": 0.1608,
      "cup_win_pct": 0.0697,
      "current_series": "4-2",
      "opponent": "PIT"
    },
    {
      "team": "VGK",
      "name": "Vegas Golden Knights",
      "round1_win_pct": 1.0,
      "round2_win_pct": 0.5556,
      "round3_win_pct": 0.1429,
      "cup_win_pct": 0.0504,
      "current_series": "4-2",
      "opponent": "UTA"
    },
    {
      "team": "MTL",
      "name": "Montr\u00e9al Canadiens",
      "round1_win_pct": 1.0,
      "round2_win_pct": 0.4023,
      "round3_win_pct": 0.1383,
      "cup_win_pct": 0.0476,
      "current_series": "4-3",
      "opponent": "TBL"
    },
    {
      "team": "ANA",
      "name": "Anaheim Ducks",
      "round1_win_pct": 1.0,
      "round2_win_pct": 0.4444,
      "round3_win_pct": 0.1071,
      "cup_win_pct": 0.0349,
      "current_series": "4-2",
      "opponent": "EDM"
    },
    {
      "team": "MIN",
      "name": "Minnesota Wild",
      "round1_win_pct": 1.0,
      "round2_win_pct": 0.1751,
      "round3_win_pct": 0.0756,
      "cup_win_pct": 0.0288,
      "current_series": "4-2",
      "opponent": "DAL"
    },
    {
      "team": "BOS",
      "name": "Boston Bruins",
      "round1_win_pct": 0.0,
      "round2_win_pct": 0.0,
      "round3_win_pct": 0.0,
      "cup_win_pct": 0.0,
      "current_series": "2-4",
      "opponent": "BUF"
    },
    {
      "team": "TBL",
      "name": "Tampa Bay Lightning",
      "round1_win_pct": 0.0,
      "round2_win_pct": 0.0,
      "round3_win_pct": 0.0,
      "cup_win_pct": 0.0,
      "current_series": "3-4",
      "opponent": "MTL"
    },
    {
      "team": "OTT",
      "name": "Ottawa Senators",
      "round1_win_pct": 0.0,
      "round2_win_pct": 0.0,
      "round3_win_pct": 0.0,
      "cup_win_pct": 0.0,
      "current_series": "0-4",
      "opponent": "CAR"
    },
    {
      "team": "PIT",
      "name": "Pittsburgh Penguins",
      "round1_win_pct": 0.0,
      "round2_win_pct": 0.0,
      "round3_win_pct": 0.0,
      "cup_win_pct": 0.0,
      "current_series": "2-4",
      "opponent": "PHI"
    },
    {
      "team": "LAK",
      "name": "Los Angeles Kings",
      "round1_win_pct": 0.0,
      "round2_win_pct": 0.0,
      "round3_win_pct": 0.0,
      "cup_win_pct": 0.0,
      "current_series": "0-4",
      "opponent": "COL"
    },
    {
      "team": "DAL",
      "name": "Dallas Stars",
      "round1_win_pct": 0.0,
      "round2_win_pct": 0.0,
      "round3_win_pct": 0.0,
      "cup_win_pct": 0.0,
      "current_series": "2-4",
      "opponent": "MIN"
    },
    {
      "team": "UTA",
      "name": "Utah Mammoth",
      "round1_win_pct": 0.0,
      "round2_win_pct": 0.0,
      "round3_win_pct": 0.0,
      "cup_win_pct": 0.0,
      "current_series": "2-4",
      "opponent": "VGK"
    },
    {
      "team": "EDM",
      "name": "Edmonton Oilers",
      "round1_win_pct": 0.0,
      "round2_win_pct": 0.0,
      "round3_win_pct": 0.0,
      "cup_win_pct": 0.0,
      "current_series": "2-4",
      "opponent": "ANA"
    }
  ]
}