{
  "active": [
    {
      "series_id": "BUF-BOS",
      "round": 1,
      "seed": "D1 vs WC1",
      "home": {
        "team": "BUF",
        "name": "Buffalo Sabres",
        "wins": 1,
        "series_win_pct": 0.5475
      },
      "away": {
        "team": "BOS",
        "name": "Boston Bruins",
        "wins": 1,
        "series_win_pct": 0.4525
      },
      "length_distribution": {
        "4": 0.0,
        "5": 0.24925,
        "6": 0.376,
        "7": 0.37475
      },
      "joint_distribution": {
        "home": {
          "4": 0.0,
          "5": 0.15225,
          "6": 0.224375,
          "7": 0.170875
        },
        "away": {
          "4": 0.0,
          "5": 0.097,
          "6": 0.151625,
          "7": 0.203875
        }
      },
      "most_likely": {
        "winner": "BUF",
        "games": "6"
      },
      "drivers": [
        {
          "feature": "a_sf",
          "label": "Away shots-for/gm",
          "shap": 0.2132,
          "favors": "home",
          "value": 27.024
        },
        {
          "feature": "a_pp",
          "label": "Away power play %",
          "shap": -0.1397,
          "favors": "away",
          "value": 0.234
        },
        {
          "feature": "d_point_pct",
          "label": "Points-% edge",
          "shap": -0.0738,
          "favors": "away",
          "value": 0.055
        }
      ]
    },
    {
      "series_id": "TBL-MTL",
      "round": 1,
      "seed": "D2 vs D3",
      "home": {
        "team": "TBL",
        "name": "Tampa Bay Lightning",
        "wins": 1,
        "series_win_pct": 0.6926
      },
      "away": {
        "team": "MTL",
        "name": "Montr\u00e9al Canadiens",
        "wins": 1,
        "series_win_pct": 0.3074
      },
      "length_distribution": {
        "4": 0.0,
        "5": 0.2815,
        "6": 0.389375,
        "7": 0.329125
      },
      "joint_distribution": {
        "home": {
          "4": 0.0,
          "5": 0.22675,
          "6": 0.296625,
          "7": 0.16925
        },
        "away": {
          "4": 0.0,
          "5": 0.05475,
          "6": 0.09275,
          "7": 0.159875
        }
      },
      "most_likely": {
        "winner": "TBL",
        "games": "6"
      },
      "drivers": [
        {
          "feature": "a_sf",
          "label": "Away shots-for/gm",
          "shap": 0.1477,
          "favors": "home",
          "value": 26.293
        },
        {
          "feature": "a_pp",
          "label": "Away power play %",
          "shap": -0.1262,
          "favors": "away",
          "value": 0.231
        },
        {
          "feature": "d_sf",
          "label": "Shots-for edge",
          "shap": -0.0792,
          "favors": "away",
          "value": 1.817
        }
      ]
    },
    {
      "series_id": "CAR-OTT",
      "round": 1,
      "seed": "D1 vs WC2",
      "home": {
        "team": "CAR",
        "name": "Carolina Hurricanes",
        "wins": 2,
        "series_win_pct": 0.7356
      },
      "away": {
        "team": "OTT",
        "name": "Ottawa Senators",
        "wins": 0,
        "series_win_pct": 0.2644
      },
      "length_distribution": {
        "4": 0.153625,
        "5": 0.24575,
        "6": 0.2775,
        "7": 0.323125
      },
      "joint_distribution": {
        "home": {
          "4": 0.153625,
          "5": 0.24575,
          "6": 0.16925,
          "7": 0.167
        },
        "away": {
          "4": 0.0,
          "5": 0.0,
          "6": 0.10825,
          "7": 0.156125
        }
      },
      "most_likely": {
        "winner": "CAR",
        "games": "5"
      },
      "drivers": [
        {
          "feature": "h_sf",
          "label": "Home shots-for/gm",
          "shap": -0.1893,
          "favors": "away",
          "value": 32.159
        },
        {
          "feature": "h_sa",
          "label": "Home shots-against/gm",
          "shap": 0.1868,
          "favors": "home",
          "value": 23.927
        },
        {
          "feature": "a_pp",
          "label": "Away power play %",
          "shap": -0.1064,
          "favors": "away",
          "value": 0.24
        }
      ]
    },
    {
      "series_id": "PIT-PHI",
      "round": 1,
      "seed": "D2 vs D3",
      "home": {
        "team": "PIT",
        "name": "Pittsburgh Penguins",
        "wins": 0,
        "series_win_pct": 0.0246
      },
      "away": {
        "team": "PHI",
        "name": "Philadelphia Flyers",
        "wins": 3,
        "series_win_pct": 0.9754
      },
      "length_distribution": {
        "4": 0.771125,
        "5": 0.071,
        "6": 0.122,
        "7": 0.035875
      },
      "joint_distribution": {
        "home": {
          "4": 0.0,
          "5": 0.0,
          "6": 0.0,
          "7": 0.024625
        },
        "away": {
          "4": 0.771125,
          "5": 0.071,
          "6": 0.122,
          "7": 0.01125
        }
      },
      "most_likely": {
        "winner": "PHI",
        "games": "4"
      },
      "drivers": [
        {
          "feature": "d_gf",
          "label": "Scoring edge",
          "shap": -0.2828,
          "favors": "away",
          "value": 0.61
        },
        {
          "feature": "d_pp",
          "label": "Power-play edge",
          "shap": 0.1235,
          "favors": "home",
          "value": 0.084
        },
        {
          "feature": "a_sf",
          "label": "Away shots-for/gm",
          "shap": 0.0996,
          "favors": "home",
          "value": 25.463
        }
      ]
    },
    {
      "series_id": "COL-LAK",
      "round": 1,
      "seed": "D1 vs WC2",
      "home": {
        "team": "COL",
        "name": "Colorado Avalanche",
        "wins": 2,
        "series_win_pct": 0.9427
      },
      "away": {
        "team": "LAK",
        "name": "Los Angeles Kings",
        "wins": 0,
        "series_win_pct": 0.0573
      },
      "length_distribution": {
        "4": 0.199125,
        "5": 0.4215,
        "6": 0.171625,
        "7": 0.20775
      },
      "joint_distribution": {
        "home": {
          "4": 0.199125,
          "5": 0.4215,
          "6": 0.148875,
          "7": 0.17325
        },
        "away": {
          "4": 0.0,
          "5": 0.0,
          "6": 0.02275,
          "7": 0.0345
        }
      },
      "most_likely": {
        "winner": "COL",
        "games": "5"
      },
      "drivers": [
        {
          "feature": "h_sa",
          "label": "Home shots-against/gm",
          "shap": 0.1854,
          "favors": "home",
          "value": 26.134
        },
        {
          "feature": "d_gd",
          "label": "Goal-diff edge",
          "shap": 0.1425,
          "favors": "home",
          "value": 1.451
        },
        {
          "feature": "h_sf",
          "label": "Home shots-for/gm",
          "shap": 0.1262,
          "favors": "home",
          "value": 33.732
        }
      ]
    },
    {
      "series_id": "DAL-MIN",
      "round": 1,
      "seed": "D2 vs D3",
      "home": {
        "team": "DAL",
        "name": "Dallas Stars",
        "wins": 2,
        "series_win_pct": 0.6365
      },
      "away": {
        "team": "MIN",
        "name": "Minnesota Wild",
        "wins": 1,
        "series_win_pct": 0.3635
      },
      "length_distribution": {
        "4": 0.0,
        "5": 0.214625,
        "6": 0.36025,
        "7": 0.425125
      },
      "joint_distribution": {
        "home": {
          "4": 0.0,
          "5": 0.214625,
          "6": 0.2025,
          "7": 0.219375
        },
        "away": {
          "4": 0.0,
          "5": 0.0,
          "6": 0.15775,
          "7": 0.20575
        }
      },
      "most_likely": {
        "winner": "DAL",
        "games": "7"
      },
      "drivers": [
        {
          "feature": "h_sa",
          "label": "Home shots-against/gm",
          "shap": 0.2817,
          "favors": "home",
          "value": 26.159
        },
        {
          "feature": "a_pp",
          "label": "Away power play %",
          "shap": -0.0942,
          "favors": "away",
          "value": 0.252
        },
        {
          "feature": "a_sf",
          "label": "Away shots-for/gm",
          "shap": 0.0881,
          "favors": "home",
          "value": 29.183
        }
      ]
    },
    {
      "series_id": "VGK-UTA",
      "round": 1,
      "seed": "D1 vs WC1",
      "home": {
        "team": "VGK",
        "name": "Vegas Golden Knights",
        "wins": 1,
        "series_win_pct": 0.4512
      },
      "away": {
        "team": "UTA",
        "name": "Utah Mammoth",
        "wins": 1,
        "series_win_pct": 0.5488
      },
      "length_distribution": {
        "4": 0.0,
        "5": 0.197125,
        "6": 0.43425,
        "7": 0.368625
      },
      "joint_distribution": {
        "home": {
          "4": 0.0,
          "5": 0.07175,
          "6": 0.10625,
          "7": 0.27325
        },
        "away": {
          "4": 0.0,
          "5": 0.125375,
          "6": 0.328,
          "7": 0.095375
        }
      },
      "most_likely": {
        "winner": "UTA",
        "games": "6"
      },
      "drivers": [
        {
          "feature": "h_sa",
          "label": "Home shots-against/gm",
          "shap": 0.2331,
          "favors": "home",
          "value": 24.39
        },
        {
          "feature": "a_sf",
          "label": "Away shots-for/gm",
          "shap": 0.1212,
          "favors": "home",
          "value": 27.707
        },
        {
          "feature": "a_pp",
          "label": "Away power play %",
          "shap": 0.1175,
          "favors": "home",
          "value": 0.2
        }
      ]
    },
    {
      "series_id": "EDM-ANA",
      "round": 1,
      "seed": "D2 vs D3",
      "home": {
        "team": "EDM",
        "name": "Edmonton Oilers",
        "wins": 1,
        "series_win_pct": 0.3859
      },
      "away": {
        "team": "ANA",
        "name": "Anaheim Ducks",
        "wins": 1,
        "series_win_pct": 0.6141
      },
      "length_distribution": {
        "4": 0.0,
        "5": 0.235625,
        "6": 0.4085,
        "7": 0.355875
      },
      "joint_distribution": {
        "home": {
          "4": 0.0,
          "5": 0.0655,
          "6": 0.097625,
          "7": 0.22275
        },
        "away": {
          "4": 0.0,
          "5": 0.170125,
          "6": 0.310875,
          "7": 0.133125
        }
      },
      "most_likely": {
        "winner": "ANA",
        "games": "6"
      },
      "drivers": [
        {
          "feature": "d_pp",
          "label": "Power-play edge",
          "shap": 0.241,
          "favors": "home",
          "value": 0.121
        },
        {
          "feature": "d_gd",
          "label": "Goal-diff edge",
          "shap": -0.1215,
          "favors": "away",
          "value": 0.488
        },
        {
          "feature": "h_pk",
          "label": "Home penalty kill %",
          "shap": -0.0906,
          "favors": "away",
          "value": 0.778
        }
      ]
    }
  ]
}